odoo10_addon_mail_notify_bounce-10.0.1.0.2-py2.7-nspkg.pth
odoo/addons/mail_notify_bounce/README.rst
odoo/addons/mail_notify_bounce/__init__.py
odoo/addons/mail_notify_bounce/__manifest__.py
odoo/addons/mail_notify_bounce/models/__init__.py
odoo/addons/mail_notify_bounce/models/fetchmail.py
odoo/addons/mail_notify_bounce/models/mail_thread.py
odoo/addons/mail_notify_bounce/static/description/icon.png
odoo/addons/mail_notify_bounce/tests/__init__.py
odoo/addons/mail_notify_bounce/tests/test_mail_notify_bounce.py
odoo/addons/mail_notify_bounce/tests/data/bounce_message
odoo/addons/mail_notify_bounce/tests/data/bounce_message_2
odoo/addons/mail_notify_bounce/views/fetchmail_view.xml
odoo10_addon_mail_notify_bounce-10.0.1.0.2.dist-info/DESCRIPTION.rst
odoo10_addon_mail_notify_bounce-10.0.1.0.2.dist-info/METADATA
odoo10_addon_mail_notify_bounce-10.0.1.0.2.dist-info/RECORD
odoo10_addon_mail_notify_bounce-10.0.1.0.2.dist-info/WHEEL
odoo10_addon_mail_notify_bounce-10.0.1.0.2.dist-info/metadata.json
odoo10_addon_mail_notify_bounce-10.0.1.0.2.dist-info/namespace_packages.txt
odoo10_addon_mail_notify_bounce-10.0.1.0.2.dist-info/top_level.txt
